pysampleboro/__init__.py
pysampleboro/main.py
pysampleboro/py.typed
pysampleboro-0.3.0.dist-info/LICENSE
pysampleboro-0.3.0.dist-info/WHEEL
pysampleboro-0.3.0.dist-info/METADATA
pysampleboro-0.3.0.dist-info/RECORD
