Metadata-Version: 2.1
Name: pysampleboro
Version: 0.3.0
Summary: My Python package to help you get up to speed.
Home-page: https://github.com/alborotogarcia/pysampleboro
License: MIT
Author: Alvaro Gallego
Author-email: agallego@achlys.tech
Requires-Python: >=3.7,<4.0
Classifier: Development Status :: 2 - Pre-Alpha
Classifier: Intended Audience :: Developers
Classifier: License :: OSI Approved :: MIT License
Classifier: Natural Language :: English
Classifier: Operating System :: OS Independent
Classifier: Programming Language :: Python :: 3
Classifier: Programming Language :: Python :: 3.7
Classifier: Programming Language :: Python :: 3.8
Classifier: Programming Language :: Python :: 3.9
Classifier: Programming Language :: Python :: 3.10
Classifier: Programming Language :: Python :: 3.11
Classifier: Topic :: Software Development :: Libraries
Provides-Extra: docs
Requires-Dist: Sphinx (>=5.0,<6.0); extra == "docs"
Requires-Dist: myst-parser (>=0.18,<0.19); extra == "docs"
Requires-Dist: packaging (>=21.3,<22.0)
Requires-Dist: sphinx-rtd-theme (>=1.0,<2.0); extra == "docs"
Project-URL: Bug Tracker, https://github.com/alborotogarcia/pysampleboro/issues
Project-URL: Changelog, https://github.com/alborotogarcia/pysampleboro/blob/master/CHANGELOG.md
Project-URL: Documentation, https://pysampleboro.readthedocs.io
Project-URL: Repository, https://github.com/alborotogarcia/pysampleboro
